tool_prep_data/__init__.py
tool_prep_data/data_prep.py
tool_prep_data-0.0.1.dist-info/METADATA
tool_prep_data-0.0.1.dist-info/WHEEL
tool_prep_data-0.0.1.dist-info/top_level.txt
tool_prep_data-0.0.1.dist-info/RECORD
