Metadata-Version: 2.1
Name: tool-prep-data
Version: 0.0.1
Summary: Incubeta first Python package
Home-page: UNKNOWN
Author: Chigozie Boniface
Author-email: chigface@yahoo.com
License: UNKNOWN
Keywords: python,first package
Platform: UNKNOWN
Classifier: Development Status :: 3 - Alpha
Classifier: Intended Audience :: Education
Classifier: Programming Language :: Python :: 2
Classifier: Programming Language :: Python :: 3
Classifier: Operating System :: MacOS :: MacOS X
Classifier: Operating System :: Microsoft :: Windows
Requires-Dist: scikit-learn
Requires-Dist: pandas
Requires-Dist: numpy
